lark_util/__init__.py
lark_util/examples/__init__.py
lark_util/examples/bitable_record_service_example.py
lark_util/examples/field_escape_example.py
lark_util/examples/lark_auth_example.py
lark_util/examples/lark_bitable_create_example.py
lark_util/examples/lark_bitable_delete_example.py
lark_util/examples/lark_bitable_search_example.py
lark_util/examples/lark_bitable_update_example.py
lark_util/examples/lark_space_node_example.py
lark_util/examples/mock_record.py
lark_util/lark_auth/__init__.py
lark_util/lark_auth/get_tenant_access_token.py
lark_util/lark_bitable/__init__.py
lark_util/lark_bitable/bitable_field_type.py
lark_util/lark_bitable/bitable_record.py
lark_util/lark_bitable/bitable_record_service.py
lark_util/lark_bitable/create_bitable_record.py
lark_util/lark_bitable/delete_bitable_record.py
lark_util/lark_bitable/search_bitable_records.py
lark_util/lark_bitable/update_bitable_record.py
lark_util/lark_client/__init__.py
lark_util/lark_space/__init__.py
lark_util/lark_space/get_space_node.py
util/json_util.py
lark_util-0.1.26.dist-info/METADATA
lark_util-0.1.26.dist-info/WHEEL
lark_util-0.1.26.dist-info/entry_points.txt
lark_util-0.1.26.dist-info/top_level.txt
lark_util-0.1.26.dist-info/RECORD
