Metadata-Version: 2.4
Name: lark_util
Version: 0.1.26
Summary: Lark API utilities
Requires-Python: >=3.10
Requires-Dist: requests
Requires-Dist: python-dotenv
Requires-Dist: lark-oapi
Provides-Extra: dev
Requires-Dist: pytest; extra == "dev"
Requires-Dist: pytest-cov; extra == "dev"
